{
  "kind": "collectionType",
  "collectionName": "appointments",
  "info": {
    "singularName": "appointment",
    "pluralName": "appointments",
    "displayName": "Appointment",
    "description": ""
  },
  "options": {
    "draftAndPublish": true
  },
  "pluginOptions": {},
  "attributes": {
    "UserName": {
      "type": "string"
    },
    "Email": {
      "type": "email"
    },
    "Date": {
      "type": "string"
    },
    "Time": {
      "type": "string"
    },
    "hospital": {
      "type": "relation",
      "relation": "manyToOne",
      "target": "api::hospital.hospital",
      "inversedBy": "appointments"
    },
    "Note": {
      "type": "richtext"
    },
    "doctor": {
      "type": "relation",
      "relation": "manyToOne",
      "target": "api::doctor.doctor",
      "inversedBy": "appointments"
    }
  }
}
